threadful/__about__.py
threadful/__init__.py
threadful/bonus.py
threadful/core.py
threadful/py.typed
threadful-0.5.1.dist-info/METADATA
threadful-0.5.1.dist-info/WHEEL
threadful-0.5.1.dist-info/licenses/LICENSE
threadful-0.5.1.dist-info/RECORD
