Metadata-Version: 2.4
Name: threadful
Version: 0.5.1
Summary: Python Threads - from Dreadful to Threadful
Project-URL: Documentation, https://github.com/robinvandernoord/threadful#readme
Project-URL: Issues, https://github.com/robinvandernoord/threadful/issues
Project-URL: Source, https://github.com/robinvandernoord/threadful
Author-email: Robin van der Noord <robinvandernoord@gmail.com>
License-Expression: MIT
License-File: LICENSE
Classifier: Development Status :: 4 - Beta
Classifier: Programming Language :: Python
Classifier: Programming Language :: Python :: 3.11
Classifier: Programming Language :: Python :: 3.12
Classifier: Programming Language :: Python :: 3.13
Classifier: Programming Language :: Python :: 3.14
Classifier: Programming Language :: Python :: Implementation :: CPython
Classifier: Programming Language :: Python :: Implementation :: PyPy
Requires-Python: >=3.11
Requires-Dist: result
Provides-Extra: dev
Requires-Dist: edwh; extra == 'dev'
Requires-Dist: hatch; extra == 'dev'
Requires-Dist: pytest-mypy-testing; extra == 'dev'
Requires-Dist: python-semantic-release<8; extra == 'dev'
Requires-Dist: su6[all]; extra == 'dev'
